[
  {
    "content": "출발전 준비사항 1. 예방접종등 필요서류 챙기기 \n 2. 대중교통별관련규정이 다르므로 이동장(케이지) 사이즈, 이용 가능 반려동물 무게를 미리체크하기 \n 3. 이동장 준비, 목줄(1.5m ~ 2m이내)과 입마개 착용하기 *맹견의 경우 입마개 필수 \n",
    "metadata": {
      "source": "대한민국 구석구석",
      "image_file": "part01_01.png",
      "part_id": "part01"
    }
  },
  {
    "content": "대중교통탑승시주의사항\n 1. 대중교통 안에서 이동장 열지 않기 \n 2. 반려동물 지정 좌석이 없을시 이동장은 좌석 아래 놓기\n 3. 반려동물 소리, 행동, 냄새 등으로 다른 고객에게 불편을 주지 않도록 주의하기\n 4. 이동장에 물과 배변패드는 필수로 넣어서 가져가기 \n 5. 심하게 짖거나 공격이 있는 반려동물의 경우 펫 전용 택시나 자차 이용하기",
    "metadata": {
      "source": "대한민국 구석구석",
      "image_file": "part01_01.png",
      "part_id": "part02"
    }
  },
  {
    "content": ["안내견은 항상 동반 탑승이 가능 ",
                "시각, 청각, 지체장애인 보조견의 경우 장애인의 원활한 대중교통 이용을 위해 동반 탑승허용"
                ]
    ,
    "metadata": {
      "source": "대한민국 구석구석",
      "image_file": "part01_01.png",
      "part_id": "part03"
    }
  },
  {
    "content": "국내선 비행기 탑승전알아두기 \n 1. 이동장 조건 확인 및 연락처 기입 \n 잠금장치가 있고 바닥이 밀폐되어 있는 것, 크기등 항공사별 이동장 조건 확인 \n 이동장 외부에 영문 성명과 비상연락처를 기입 \n 2. 탑승 방법 선택 \n 기내에 반려동물이 같이 탑승하는 방법 \n 기내가 아닌, 화물칸에 탑승하는 방법 \n 3.항공기 별 최대 마리 수 제한 \n 선착순으로 신청이 마감되며, 탑승 규정에 부합하더라도 비행기 한대의 최대 허용 마리수를 넘는다면 탑승이 불가능할 수 있음 4. 승객 1인당, 1마리만 반입가능\n 예외적으로 2마리를 같은 이동장에 넣어 반입 가능한 경우도 있으니 항공사별 조건 확인(6개월 미만의 반려동물등) \n 5. 탑승 제외 기준확인 \n 맹견과 단두종, 임신중인 동물, 생후 8주 이하 등은 제한\n 6.챙기면 좋을 것들 좋아하는 장난감이나 담요로 안정감을 주기 멀미를 대비하기 위해 탑승 2~5시간전 공복 유지하기",
    "metadata": {
      "source": "대한민국 구석구석",
      "image_file": "part02_01.png",
      "part_id": "part04"
    }
  },
  {
    "content": "국내선 비행기 탑승전알아두기\n 1.항공사별 규정체크 항공사 별로 탑승 규정(이동장 크기, 무게 마릿수 등)이 다르므로 각 항공사별 서비스 센터에 문의하기 '항공사별 탑승규정' 참고 \n 2. 반려동물운송서비스사전신청 운송 서약서 작성 항공사별 필요서류가 다를 수 있으므로 사전확인 필수 \n 3. 반려동물 수속후 탑승\n 반려동물 탑승 가능 여부 확인과 운송요금 지불",
    "metadata": {
      "source": "대한민국 구석구석",
      "image_file": "part02_02.png",
      "part_id": "part05"
    }
  },
  {
    "content": "항공사별 탑승 규정\n 탑승 규정은 항공사 사정에 따라 변동될수 있으므로 반드시 공식 홈페이지에서 확인 바랍니다.",
    "metadata": {
      "source": "대한민국 구석구석",
      "image_file": "part02_03.png",
      "part_id": "part06"
    }
  },
  {
    "content": "항공사별 탑승 규정\n 탑승 규정은 항공사 사정에 따라 변동될수 있으므로 반드시 공식 홈페이지에서 확인 바랍니다.",
    "metadata": {
      "source": "대한민국 구석구석",
      "image_file": "part02_03.png",
      "part_id": "part07"
    }
  },
  {
    "content": "코레일(KTX,무궁화호,새마을호) & SRT 탑승 규정은 철도 사정에 따라 변동될 수 있으므로 반드시 공식홈페이지에서 확인 바랍니다. \n 준비서류: 광견병 등의 예방접종 증명서류\n 탑승가능 동물: 개, 고양이 등의 소형 동물(투견, 맹금류, 뱀 등은 불가)\n 이동장 크기: 45cmx30cmx25cm 내외(길이 x 높이 x 폭) 허용 무게 : 10kg 이내(반려 동물 + 이동장 무게 합) \n 반려동물 지정 좌석: 코레일은 1.좌석을 지정하지 않으면 무임 2. 반려동물 동반 좌석이 필요한 경우 성인 요금제 결제, SRT는 좌석 지정 불가, 반려동물이 담겨있는 이동장은 좌석 발밑에 둘것",
    "metadata": {
      "source": "대한민국 구석구석",
      "image_file": "part03_01.png",
      "part_id": "part08"
    }
  },
  {
    "content": "버스(고속버스, 시내•시외버스) \n 1.이동장 크기 : 50cm X 40cm X 20cm 미만\n 2.무게: 10kg 이하(반려동물 + 이동장 무게합) \n 3.반려동물 동반 시, 해당 운송사 및 기사에게 사전 통보 및 허락 필요 \n * 고속버스는 전국 고속버스 운송사업조합에 속하는 일부 운송사만 해당 *이 외의 운송사는 규정이 다를 수 있으므로 터미널 혹은 버스 운송사에게 개별 문의 필요 \n * 각 운송사에 따라 반려동물 동승에 관해 제재가 가능 ",
    "metadata": {
      "source": "대한민국 구석구석",
      "image_file": "part04_01.png",
      "part_id": "part09"
    }
  },
  {
    "content": "일반 택시 \n 이동장이나 켄넬 안에 넣을 경우 탑승 가능 * 펫 택시 : 펫 택시는 배변패드 등 반려동물이 쾌적하게 이용할 수 있는 반려동물 맞춤형 택시 카카오 T(펫 택시), 펫글 T, 그랫 펫택시 등",
    "metadata": {
      "source": "대한민국 구석구석",
      "image_file": "part04_01.png",
      "part_id": "part10"
    }
  },
  {
    "content": "지하철 \n 1. 반려동물을 이동장비에 넣어 보이지 않게 하기 \n 2. 불쾌한 냄새가 발생하지 않게하는 등 다른 여객에게 불편을 줄 염려가 없도록 안전조치를 취하기 이를 위반하면 탑승이 거절될 수 있음",
    "metadata": {
      "source": "대한민국 구석구석",
      "image_file": "part04_01.png",
      "part_id": "part11"
    }
  }
]